<annotation>
	<folder>images</folder>
	<filename>faishalls (261).jpg</filename>
	<path>D:\project-flutter\news dataset\faishal\images\faishalls (261).jpg</path>
	<source>
		<database>Unknown</database>
	</source>
	<size>
		<width>513</width>
		<height>913</height>
		<depth>3</depth>
	</size>
	<segmented>0</segmented>
	<object>
		<name>faishal</name>
		<pose>Unspecified</pose>
		<truncated>0</truncated>
		<difficult>0</difficult>
		<bndbox>
			<xmin>138</xmin>
			<ymin>192</ymin>
			<xmax>366</xmax>
			<ymax>500</ymax>
		</bndbox>
	</object>
</annotation>
